{
  "appPageId" : "2746e722-1a11-406a-a340-af73d0c0847c",
  "componentName" : "siteforce:sldsOneColLayout",
  "dataProviders" : [ ],
  "id" : "15494ffa-5140-4497-8324-aa2d2639b1ca",
  "label" : "Account Management",
  "regions" : [ {
    "id" : "9414fe70-a24f-4c0f-9c7f-03e18c61304e",
    "regionName" : "header",
    "type" : "region"
  }, {
    "components" : [ {
      "componentAttributes" : {
        "richTextValue" : "             <h1 style=\"text-align: center;\">                 <b style=\"font-size: 20px; color: #1e2443;\">Account Management</b>             </h1>             "
      },
      "componentName" : "forceCommunity:richTextInline",
      "id" : "eb8dda68-5c22-4c18-ba9b-021915f597d4",
      "renderPriority" : "NEUTRAL",
      "renditionMap" : { },
      "type" : "component"
    }, {
      "componentAttributes" : {
        "tabsetConfig" : {
          "UUID" : "505dc903-972c-41d4-94a3-e11ae21a40a0",
          "activeTab" : "tab1",
          "tabs" : [ {
            "UUID" : "81ab7e38-b6f3-4c9a-9dbb-6a520d47134e",
            "allowGuestUser" : false,
            "locked" : false,
            "seedComponents" : [ {
              "attributes" : {
                "customTitle" : "Members",
                "parentRecordId" : "{!CurrentUser.accountId}",
                "relatedListName" : "Users",
                "showBreadCrumbs" : "false",
                "showCustomTitle" : "true",
                "showManualRefreshButton" : "false",
                "showRowNumbers" : "false"
              },
              "fqn" : "forceCommunity:relatedList"
            } ],
            "tabKey" : "tab1",
            "tabName" : "Members"
          }, {
            "UUID" : "16502b25-f4e4-444d-9974-c6a3df033752",
            "allowGuestUser" : false,
            "locked" : false,
            "seedComponents" : [ {
              "attributes" : {
                "recordId" : "{!CurrentUser.accountId}"
              },
              "fqn" : "forceCommunity:accountBrandRecord"
            } ],
            "tabKey" : "tab2",
            "tabName" : "Branding"
          } ],
          "useOverflowMenu" : false
        }
      },
      "componentName" : "forceCommunity:tabset",
      "id" : "505dc903-972c-41d4-94a3-e11ae21a40a0",
      "regions" : [ {
        "components" : [ {
          "componentAttributes" : {
            "customTitle" : "Members",
            "parentRecordId" : "{!CurrentUser.accountId}",
            "relatedListName" : "Users",
            "showBreadCrumbs" : false,
            "showCustomTitle" : true,
            "showManualRefreshButton" : false,
            "showRowNumbers" : false
          },
          "componentName" : "forceCommunity:relatedList",
          "id" : "da0de3fb-2ce5-4919-b335-4862cb72c14f",
          "renditionMap" : { },
          "type" : "component"
        } ],
        "id" : "81ab7e38-b6f3-4c9a-9dbb-6a520d47134e",
        "regionLabel" : "Members",
        "regionName" : "tab1",
        "renditionMap" : { },
        "type" : "region"
      }, {
        "components" : [ {
          "componentAttributes" : {
            "recordId" : "{!CurrentUser.accountId}"
          },
          "componentName" : "forceCommunity:accountBrandRecord",
          "id" : "b442b276-04b2-4e2e-8031-09862a27f645",
          "renditionMap" : { },
          "type" : "component"
        } ],
        "id" : "16502b25-f4e4-444d-9974-c6a3df033752",
        "regionLabel" : "Branding",
        "regionName" : "tab2",
        "renditionMap" : { },
        "type" : "region"
      } ],
      "renderPriority" : "NEUTRAL",
      "renditionMap" : { },
      "type" : "component"
    } ],
    "id" : "048b350d-a528-40e0-83e0-ed2de2984fac",
    "regionName" : "content",
    "type" : "region"
  }, {
    "id" : "af83434f-f142-4432-8642-47a0474d97a7",
    "regionName" : "footer",
    "type" : "region"
  }, {
    "components" : [ {
      "componentAttributes" : {
        "customHeadTags" : "",
        "description" : "",
        "title" : "Account Management"
      },
      "componentName" : "forceCommunity:seoAssistant",
      "id" : "eb65507a-0611-4ef5-ac00-d53cfb73524b",
      "renditionMap" : { },
      "type" : "component"
    } ],
    "id" : "7d36dc24-ff87-4eb2-b85b-0f4405a58b37",
    "regionName" : "sfdcHiddenRegion",
    "type" : "region"
  } ],
  "themeLayoutType" : "Inner",
  "type" : "view",
  "viewType" : "account-management"
}