{
  "appPageId" : "2746e722-1a11-406a-a340-af73d0c0847c",
  "componentName" : "siteforce:sldsOneColLayout",
  "dataProviders" : [ ],
  "id" : "5b2159e7-360e-42ca-9b19-41da381a96b1",
  "label" : "Topic Catalog",
  "regions" : [ {
    "components" : [ {
      "componentAttributes" : {
        "bannerText" : "",
        "bannerTextWithKnowledge" : "Explore other <a href=\"javascript:void(0)\" class=\"headlineArticles\">articles</a> and <a href=\"javascript:void(0)\" class=\"headlineDiscussions\">discussions</a> on this topic.",
        "bannerTextWithoutKnowledge" : "Explore other <a href=\"javascript:void(0)\" class=\"headlineDiscussions\">discussions</a> on this topic.",
        "pageType" : "",
        "showSubTopics" : true,
        "title" : "Topics",
        "uniqueNameOrId" : ""
      },
      "componentName" : "forceCommunity:headline",
      "id" : "6eafc07a-bbf2-47b6-942a-ec8f2f288508",
      "renderPriority" : "NEUTRAL",
      "renditionMap" : { },
      "type" : "component"
    } ],
    "id" : "a193313a-8790-45b3-a656-ffd8a3827d15",
    "regionName" : "header",
    "type" : "region"
  }, {
    "components" : [ {
      "componentAttributes" : { },
      "componentName" : "forceCommunity:topicCatalog",
      "id" : "dc13d89c-1a33-4946-8558-5ea7b2f52b7a",
      "renderPriority" : "NEUTRAL",
      "renditionMap" : { },
      "type" : "component"
    } ],
    "id" : "e313eb64-06c4-4581-9dd8-0a10538329f8",
    "regionName" : "content",
    "type" : "region"
  }, {
    "id" : "4d02c767-a7cf-422e-b55d-1c6f978c57e9",
    "regionName" : "footer",
    "type" : "region"
  }, {
    "components" : [ {
      "componentAttributes" : {
        "customHeadTags" : "",
        "description" : "",
        "title" : "Topic Catalog"
      },
      "componentName" : "forceCommunity:seoAssistant",
      "id" : "8f0cb02f-69f3-4314-ab5e-cc33ae8a8bda",
      "renditionMap" : { },
      "type" : "component"
    } ],
    "id" : "a4e007ab-aba2-40bf-ad1c-b0dc7ac0584b",
    "regionName" : "sfdcHiddenRegion",
    "type" : "region"
  } ],
  "themeLayoutType" : "Inner",
  "type" : "view",
  "viewType" : "topic-catalog"
}